Metadata-Version: 2.1
Name: python-project-stub
Version: 0.0.23
Summary: Stub files to use as the basis of a Python project that can be packaged and uploaded to PyPI
Home-page: https://github.com/striebel/python-project-stub
Author: Jacob Striebel
Author-email: jacob.striebel@example.com
License: MIT
Project-URL: Homepage, https://github.com/striebel/python-project-stub
License-File: LICENSE
